taxidTools/Lineage.py
taxidTools/Node.py
taxidTools/Taxonomy.py
taxidTools/__init__.py
taxidTools/__version__.py
taxidTools/exceptions.py
taxidTools/factories.py
taxidTools/utils.py
taxidTools-3.1.1.dist-info/LICENSE
taxidTools-3.1.1.dist-info/METADATA
taxidTools-3.1.1.dist-info/WHEEL
taxidTools-3.1.1.dist-info/top_level.txt
taxidTools-3.1.1.dist-info/RECORD
