Metadata-Version: 2.1
Name: taxidTools
Version: 3.1.1
Summary: A Python Toolkit for Taxonomy
Home-page: https://github.com/CVUA-RRW/taxidTools
Author: Gregoire Denay
Author-email: gregoire.denay@cvua-rrw.de
License: BSD License
Project-URL: Bug Tracker, https://github.com/CVUA-RRW/taxidTools/issues
Classifier: Programming Language :: Python :: 3
Classifier: License :: OSI Approved :: BSD License
Classifier: Operating System :: OS Independent
Requires-Python: >=3.9
License-File: LICENSE
